{
  "video_id": "6Sp-pr3yCkc",
  "title": "ICT Mentorship Core Content - Month 05 - How To Use Bullish Seasonal Tendencies In HTF Analysis",
  "word_count": 3124,
  "total_mentions": 13,
  "unique_concepts": 2,
  "concept_counts": {
    "market_structure": 3,
    "order_block": 10
  },
  "category_counts": {
    "market_structure": 3,
    "key_levels": 10
  },
  "top_concepts": [
    {
      "id": "order_block",
      "name": "Order Block",
      "count": 10,
      "category": "key_levels"
    },
    {
      "id": "market_structure",
      "name": "Market Structure",
      "count": 3,
      "category": "market_structure"
    }
  ],
  "mentions": [
    {
      "concept_id": "market_structure",
      "keyword": "market structure",
      "position": 8700,
      "context": "...11 we can see that the seasonal tendency had a really nice effect here after we made a nice low and Market structures shifted to the bullish side and station overflow is now bullish and during a time of year when the...",
      "match_type": "keyword",
      "start_time": 605.7,
      "end_time": 608.34
    },
    {
      "concept_id": "market_structure",
      "keyword": "structure",
      "position": 8707,
      "context": "...an see that the seasonal tendency had a really nice effect here after we made a nice low and Market structures shifted to the bullish side and station overflow is now bullish and during a time of year when the...",
      "match_type": "keyword",
      "start_time": 605.7,
      "end_time": 608.34
    },
    {
      "concept_id": "market_structure",
      "keyword": "higher high",
      "position": 8007,
      "context": "...S CAD pairs that means we would expect bullishness in here now while we didn't press up to make new higher highs there was a nice little pop nice little rally in here but overall the direction was down so you ca...",
      "match_type": "keyword",
      "start_time": 558.24,
      "end_time": 561.6
    },
    {
      "concept_id": "order_block",
      "keyword": "ob",
      "position": 248,
      "context": "...s this module is going to be teaching bullish seasonals in higher time frame analysis okay you've probably seen this chart before I've made uh available a few of these templates over the years but we're...",
      "match_type": "keyword",
      "start_time": 32.64,
      "end_time": 37.62
    },
    {
      "concept_id": "order_block",
      "keyword": "ob",
      "position": 2821,
      "context": "... and as a new Trader I could tell you I would have never answered that question with yeah I could probably agree to that um I it felt like a random thing to me and one of the things that I like about se...",
      "match_type": "keyword",
      "start_time": 211.8,
      "end_time": 214.5
    },
    {
      "concept_id": "order_block",
      "keyword": "ob",
      "position": 4028,
      "context": "...lineate at the bottom of the chart down here you can see it's all dated here's December November October this is all calendar month based this is contract delivery months okay you can see the vertical l...",
      "match_type": "keyword",
      "start_time": 284.82,
      "end_time": 290.58
    },
    {
      "concept_id": "order_block",
      "keyword": "ob",
      "position": 4531,
      "context": "...iding when would be a good time to buy well if you were paying attention you can see that this is probably a really good time to be buying around mid-march all the way up into the May June time period s...",
      "match_type": "keyword",
      "start_time": 322.14,
      "end_time": 326.94
    },
    {
      "concept_id": "order_block",
      "keyword": "ob",
      "position": 5149,
      "context": "...ng to Rally every single year march to June doesn't mean that it just means that there's a strong probability that historically looking back over 40 years worth of data and comparing it against 15 years...",
      "match_type": "keyword",
      "start_time": 364.26,
      "end_time": 368.34
    },
    {
      "concept_id": "order_block",
      "keyword": "ob",
      "position": 5389,
      "context": "...lying well there I say it element of Truth to the fact that there is a tendency for this to Rally problem is if you're not a Futures Contract Trader this doesn't do anything for you or does it if we are...",
      "match_type": "keyword",
      "start_time": 378.96,
      "end_time": 383.04
    },
    {
      "concept_id": "order_block",
      "keyword": "ob",
      "position": 6577,
      "context": "...es Contract shows for Canadian dollar Futures price so if there's a strong tenancy for September October November and December to have a decline in the Canadian dollar that should be a bullish scenario ...",
      "match_type": "keyword",
      "start_time": 456.42,
      "end_time": 462.54
    },
    {
      "concept_id": "order_block",
      "keyword": "ob",
      "position": 13562,
      "context": "... okay here's the crude oil markets the weekly chart and I just went back to January uh 14 2014. and obviously you can see here's this is a bearish market here it's been in a long-term downtrend when the...",
      "match_type": "keyword",
      "start_time": 929.58,
      "end_time": 933.12
    },
    {
      "concept_id": "order_block",
      "keyword": "ob",
      "position": 15604,
      "context": "...e in the marketplace and I'm matured now and I can look back and I can pick out where the highest probability seasonal Tendencies are for certain times of the year certain markets have really strong sea...",
      "match_type": "keyword",
      "start_time": 1052.04,
      "end_time": 1056.36
    },
    {
      "concept_id": "order_block",
      "keyword": "ob",
      "position": 16119,
      "context": "...t doesn't mean it's a guaranteed it's going to be accurate it just means that we have a high odds probability that our prognostication will lead us to a successful outcome this is just one example of ho...",
      "match_type": "keyword",
      "start_time": 1082.76,
      "end_time": 1088.52
    }
  ],
  "extracted_at": "2026-01-27T12:57:19.617498"
}